devcore.py
core/__init__.py
core/command_config.py
core/command_new_setup.py
core/command_wp_setup.py
core/db.py
core/env_manager.py
core/github_integration.py
core/template_engine.py
core/wp_dropdb.py
core/wp_init.py
devcore_cli-1.0.9.dist-info/METADATA
devcore_cli-1.0.9.dist-info/WHEEL
devcore_cli-1.0.9.dist-info/entry_points.txt
devcore_cli-1.0.9.dist-info/top_level.txt
devcore_cli-1.0.9.dist-info/RECORD
