Metadata-Version: 2.4
Name: devcore-cli
Version: 1.0.9
Summary: DevCore — WordPress & Laravel project automation CLI
Home-page: https://github.com/pujiermanto/devcore-cli
Author: Puji Ermanto | <Engineer> Aka : AA. Tarmana , Jonathan Davis, Milisi Bambu Runcing Terhalang
Author-email: puji@gmail.com
Classifier: Programming Language :: Python :: 3
Classifier: License :: OSI Approved :: MIT License
Classifier: Operating System :: OS Independent
Classifier: Topic :: Software Development :: Build Tools
Classifier: Environment :: Console
Requires-Python: >=3.8
Requires-Dist: jinja2>=3.1.2
Dynamic: author
Dynamic: author-email
Dynamic: classifier
Dynamic: description
Dynamic: description-content-type
Dynamic: home-page
Dynamic: requires-dist
Dynamic: requires-python
Dynamic: summary
